Metadata-Version: 1.0
Name: chord2vec
Version: 2.0
Summary: Embedding chords
Home-page: https://github.com/Sephora-M/chord2vec
Author: Sephora Madjiheurem
Author-email: sephora.madjiheurem@gmail.com
License: UNKNOWN
Platform: UNKNOWN
